{"id":"ID_00116","name":"Jenny's Canyon Trail","Snippet":{},"description":"<html xmlns:fo=\"http://www.w3.org/1999/XSL/Format\" xmlns:msxsl=\"urn:schemas-microsoft-com:xslt\">\n\n<head>\n\n<META http-equiv=\"Content-Type\" content=\"text/html\">\n\n<meta http-equiv=\"content-type\" content=\"text/html; charset=UTF-8\">\n\n</head>\n\n<body style=\"margin:0px 0px 0px 0px;overflow:auto;background:#FFFFFF;\">\n\n<table style=\"font-family:Arial,Verdana,Times;font-size:12px;text-align:left;width:100%;border-collapse:collapse;padding:3px 3px 3px 3px\">\n\n<tr style=\"text-align:center;font-weight:bold;background:#9CBCE2\">\n\n<td>Jenny's Canyon Trail</td>\n\n</tr>\n\n<tr>\n\n<td>\n\n<table style=\"font-family:Arial,Verdana,Times;font-size:12px;text-align:left;width:100%;border-spacing:0px; padding:3px 3px 3px 3px\">\n\n<tr>\n\n<td>Trail_Name</td>\n\n<td>Jenny's Canyon Trail</td>\n\n</tr>\n\n<tr bgcolor=\"#D4E4F3\">\n\n<td>Recreation_Area</td>\n\n<td>Snow Canyon State Park</td>\n\n</tr>\n\n<tr>\n\n<td>Reserve</td>\n\n<td>RCNCA</td>\n\n</tr>\n\n<tr bgcolor=\"#D4E4F3\">\n\n<td>Management</td>\n\n<td>State Parks</td>\n\n</tr>\n\n<tr>\n\n<td>Type</td>\n\n<td>Singletrack</td>\n\n</tr>\n\n<tr bgcolor=\"#D4E4F3\">\n\n<td>Data</td>\n\n<td>Digitized</td>\n\n</tr>\n\n<tr>\n\n<td>Miles</td>\n\n<td>0.171419</td>\n\n</tr>\n\n<tr bgcolor=\"#D4E4F3\">\n\n<td>Hike</td>\n\n<td>Yes</td>\n\n</tr>\n\n<tr>\n\n<td>Bike</td>\n\n<td>No</td>\n\n</tr>\n\n<tr bgcolor=\"#D4E4F3\">\n\n<td>Horse</td>\n\n<td>No</td>\n\n</tr>\n\n<tr>\n\n<td>Designed_Use</td>\n\n<td>Hike</td>\n\n</tr>\n\n<tr bgcolor=\"#D4E4F3\">\n\n<td>Hike_Difficulty</td>\n\n<td>&lt;Null&gt;</td>\n\n</tr>\n\n<tr>\n\n<td>Bike_Difficulty</td>\n\n<td>&lt;Null&gt;</td>\n\n</tr>\n\n<tr bgcolor=\"#D4E4F3\">\n\n<td>Surface</td>\n\n<td>Native</td>\n\n</tr>\n\n<tr>\n\n<td>Trail_Class</td>\n\n<td>&lt;Null&gt;</td>\n\n</tr>\n\n<tr bgcolor=\"#D4E4F3\">\n\n<td>ADA_Accessible</td>\n\n<td>No</td>\n\n</tr>\n\n<tr>\n\n<td>Historic_Significance</td>\n\n<td>Not Evaluated</td>\n\n</tr>\n\n<tr bgcolor=\"#D4E4F3\">\n\n<td>Track_Type</td>\n\n<td>Trail</td>\n\n</tr>\n\n<tr>\n\n<td>Motorized_Prohibited</td>\n\n<td>Yes</td>\n\n</tr>\n\n<tr bgcolor=\"#D4E4F3\">\n\n<td>Route_Type</td>\n\n<td>&lt;Null&gt;</td>\n\n</tr>\n\n<tr>\n\n<td>All_Non_Motorized_Users</td>\n\n<td>No</td>\n\n</tr>\n\n<tr bgcolor=\"#D4E4F3\">\n\n<td>URL</td>\n\n<td>&lt;Null&gt;</td>\n\n</tr>\n\n<tr>\n\n<td>Description</td>\n\n<td>&lt;Null&gt;</td>\n\n</tr>\n\n</table>\n\n</td>\n\n</tr>\n\n</table>\n\n</body>\n\n</html>","styleUrl":"#LineStyle00","MultiGeometry":{"LineString":{"extrude":"0","tessellate":"1","altitudeMode":"clampToGround","coordinates":"-113.6420147714272,37.18872653669968,0 -113.6419568991502,37.18870779977305,0 -113.6419202670447,37.18868286744731,0 -113.6418954378181,37.1885861413812,0 -113.6418681318202,37.18852094351608,0 -113.6418802332377,37.18845772816204,0 -113.6419101012298,37.18839125439812,0 -113.6419849441407,37.18838386206415,0 -113.6420707055973,37.1883819485539,0 -113.642113087986,37.18836669705365,0 -113.6422126453766,37.18835016947411,0 -113.642285011536,37.18837430426053,0 -113.6423613484357,37.18840979631893,0 -113.6424477082046,37.188425035652,0 -113.6425114315606,37.18840644646543,0 -113.6425783296735,37.18837634189241,0 -113.6426561474315,37.18835171517657,0 -113.6427015057518,37.18831923038916,0 -113.642790043305,37.1882943646761,0 -113.6428427468186,37.18826743767561,0 -113.6429096446739,37.18823733291298,0 -113.6429953059893,37.18823255897411,0 -113.6430555556858,37.18821690828535,0 -113.6431226532672,37.1881925210994,0 -113.6431762537381,37.18819132453373,0 -113.6432221102708,37.18817313381082,0 -113.6433038995293,37.18815986302973,0 -113.643392336755,37.18813213801143,0 -113.6434684751497,37.18816191072724,0 -113.6435364698195,37.18816325388622,0 -113.6435731011091,37.1881881866268,0 -113.6436238268194,37.18820708268197,0 -113.6436823976503,37.18824583074501,0 -113.6437472166717,37.18825868918381,0 -113.6437947678773,37.1882891005483,0 -113.6438775556356,37.18830441877377,0 -113.6439235109004,37.18828908664494,0 -113.6440086735238,37.18827001770001,0 -113.6440686242701,37.18824578992299,0 -113.6441433657287,37.18823553737921,0 -113.6442464957809,37.18821892808708,0 -113.6443392047353,37.18821113522822,0"}}}