{"id":"ID_00140","name":"White Domes Trail","Snippet":{},"description":"<html xmlns:fo=\"http://www.w3.org/1999/XSL/Format\" xmlns:msxsl=\"urn:schemas-microsoft-com:xslt\">\n\n<head>\n\n<META http-equiv=\"Content-Type\" content=\"text/html\">\n\n<meta http-equiv=\"content-type\" content=\"text/html; charset=UTF-8\">\n\n</head>\n\n<body style=\"margin:0px 0px 0px 0px;overflow:auto;background:#FFFFFF;\">\n\n<table style=\"font-family:Arial,Verdana,Times;font-size:12px;text-align:left;width:100%;border-collapse:collapse;padding:3px 3px 3px 3px\">\n\n<tr style=\"text-align:center;font-weight:bold;background:#9CBCE2\">\n\n<td>White Domes Trail</td>\n\n</tr>\n\n<tr>\n\n<td>\n\n<table style=\"font-family:Arial,Verdana,Times;font-size:12px;text-align:left;width:100%;border-spacing:0px; padding:3px 3px 3px 3px\">\n\n<tr>\n\n<td>Trail_Name</td>\n\n<td>White Domes Trail</td>\n\n</tr>\n\n<tr bgcolor=\"#D4E4F3\">\n\n<td>Recreation_Area</td>\n\n<td>Canaan Mountain</td>\n\n</tr>\n\n<tr>\n\n<td>Reserve</td>\n\n<td></td>\n\n</tr>\n\n<tr bgcolor=\"#D4E4F3\">\n\n<td>Management</td>\n\n<td>BLM</td>\n\n</tr>\n\n<tr>\n\n<td>Type</td>\n\n<td>Primitive Route</td>\n\n</tr>\n\n<tr bgcolor=\"#D4E4F3\">\n\n<td>Data</td>\n\n<td>Digitized</td>\n\n</tr>\n\n<tr>\n\n<td>Miles</td>\n\n<td>1.359372</td>\n\n</tr>\n\n<tr bgcolor=\"#D4E4F3\">\n\n<td>Hike</td>\n\n<td>Yes</td>\n\n</tr>\n\n<tr>\n\n<td>Bike</td>\n\n<td>No</td>\n\n</tr>\n\n<tr bgcolor=\"#D4E4F3\">\n\n<td>Horse</td>\n\n<td>No</td>\n\n</tr>\n\n<tr>\n\n<td>Designed_Use</td>\n\n<td>Hike</td>\n\n</tr>\n\n<tr bgcolor=\"#D4E4F3\">\n\n<td>Hike_Difficulty</td>\n\n<td>&lt;Null&gt;</td>\n\n</tr>\n\n<tr>\n\n<td>Bike_Difficulty</td>\n\n<td>&lt;Null&gt;</td>\n\n</tr>\n\n<tr bgcolor=\"#D4E4F3\">\n\n<td>Surface</td>\n\n<td>Native</td>\n\n</tr>\n\n<tr>\n\n<td>Trail_Class</td>\n\n<td>Minimally Developed</td>\n\n</tr>\n\n<tr bgcolor=\"#D4E4F3\">\n\n<td>ADA_Accessible</td>\n\n<td>No</td>\n\n</tr>\n\n<tr>\n\n<td>Historic_Significance</td>\n\n<td>Not Evaluated</td>\n\n</tr>\n\n<tr bgcolor=\"#D4E4F3\">\n\n<td>Track_Type</td>\n\n<td>Trail</td>\n\n</tr>\n\n<tr>\n\n<td>Motorized_Prohibited</td>\n\n<td>Yes</td>\n\n</tr>\n\n<tr bgcolor=\"#D4E4F3\">\n\n<td>Route_Type</td>\n\n<td>&lt;Null&gt;</td>\n\n</tr>\n\n<tr>\n\n<td>All_Non_Motorized_Users</td>\n\n<td>No</td>\n\n</tr>\n\n<tr bgcolor=\"#D4E4F3\">\n\n<td>URL</td>\n\n<td>&lt;Null&gt;</td>\n\n</tr>\n\n<tr>\n\n<td>Description</td>\n\n<td>&lt;Null&gt;</td>\n\n</tr>\n\n</table>\n\n</td>\n\n</tr>\n\n</table>\n\n</body>\n\n</html>","styleUrl":"#LineStyle00","MultiGeometry":{"LineString":{"extrude":"0","tessellate":"1","altitudeMode":"clampToGround","coordinates":"-112.9833163156899,37.06310558539875,0 -112.9833140502285,37.06310384342046,0 -112.9828922814293,37.0627796576736,0 -112.9825269082793,37.06242890235632,0 -112.982068185415,37.06191316788716,0 -112.981460484109,37.06137613114523,0 -112.9811223242817,37.06092975197059,0 -112.9806957667652,37.06050863937399,0 -112.9801227046911,37.06016134411838,0 -112.979576849275,37.05971842882385,0 -112.9791521618366,37.05936865163956,0 -112.9786366071618,37.05894901689289,0 -112.9779689908403,37.05838917019178,0 -112.977578311854,37.05820535735557,0 -112.9771826974724,37.05783129733791,0 -112.9769039211104,37.05738391496889,0 -112.9766022661784,37.05719861516242,0 -112.9759977249758,37.0567804513145,0 -112.975454383807,37.05643263797804,0 -112.9752961601095,37.05605461695929,0 -112.9748702794356,37.05565726143482,0 -112.9744141157141,37.05523661822374,0 -112.9739548765413,37.05469706927492,0 -112.9735914325438,37.05441762543616,0 -112.9732310706518,37.05425708444842,0 -112.9726587055049,37.05393353183449,0 -112.9721833593863,37.05391764733374,0 -112.9716153100015,37.0537605546572,0 -112.9711999218885,37.05376745978928,0 -112.9707567082329,37.05384619940739,0 -112.9702825929606,37.05387786914019,0 -112.9698387640078,37.05393282426643,0 -112.969333747676,37.05391742091488,0 -112.9689690945117,37.05359040071173,0 -112.9686390304033,37.05345313311383,0 -112.9681915159831,37.05336539689214,0 -112.9676525333613,37.05318401250778,0 -112.967146907456,37.05314481870141,0 -112.9664577366156,37.05289454605872,0 -112.9658569656026,37.05261901314786,0 -112.9654372883979,37.05245943158867,0 -112.9649267615449,37.05222998005841,0 -112.9646529842512,37.0519728139837,0 -112.9646528590472,37.05197325351736,0"}}}